[{"block_size_x": 256, "block_size_y": 2, "tile_size_x": 2, "tile_size_y": 3, "read_only": 0, "time": 4.149721622467041}, {"block_size_x": 96, "block_size_y": 2, "tile_size_x": 4, "tile_size_y": 1, "read_only": 0, "time": 7.394361591339111}, {"block_size_x": 32, "block_size_y": 8, "tile_size_x": 1, "tile_size_y": 1, "read_only": 1, "time": 6.918111896514892}, {"block_size_x": 112, "block_size_y": 8, "tile_size_x": 1, "tile_size_y": 3, "read_only": 1, "time": 4.852172756195069}, {"block_size_x": 112, "block_size_y": 4, "tile_size_x": 2, "tile_size_y": 3, "read_only": 1, "time": 3.8077439785003664}, {"block_size_x": 64, "block_size_y": 1, "tile_size_x": 2, "tile_size_y": 2, "read_only": 0, "time": 7.741126441955567}, {"block_size_x": 112, "block_size_y": 2, "tile_size_x": 2, "tile_size_y": 3, "read_only": 1, "time": 3.857145643234253}, {"block_size_x": 80, "block_size_y": 8, "tile_size_x": 2, "tile_size_y": 1, "read_only": 0, "time": 6.967360019683838}, {"block_size_x": 80, "block_size_y": 4, "tile_size_x": 3, "tile_size_y": 3, "read_only": 1, "time": 4.3925374984741214}, {"block_size_x": 64, "block_size_y": 8, "tile_size_x": 2, "tile_size_y": 1, "read_only": 0, "time": 6.817139148712158}, {"block_size_x": 128, "block_size_y": 2, "tile_size_x": 3, "tile_size_y": 3, "read_only": 0, "time": 7.719033718109131}, {"block_size_x": 48, "block_size_y": 4, "tile_size_x": 3, "tile_size_y": 2, "read_only": 1, "time": 4.614099216461182}, {"block_size_x": 208, "block_size_y": 4, "tile_size_x": 1, "tile_size_y": 2, "read_only": 1, "time": 5.222092819213867}, {"block_size_x": 160, "block_size_y": 1, "tile_size_x": 3, "tile_size_y": 3, "read_only": 1, "time": 14.753132820129395}, {"block_size_x": 16, "block_size_y": 16, "tile_size_x": 2, "tile_size_y": 1, "read_only": 1, "time": 6.601484775543213}, {"block_size_x": 48, "block_size_y": 8, "tile_size_x": 2, "tile_size_y": 3, "read_only": 1, "time": 4.61221752166748}, {"block_size_x": 208, "block_size_y": 4, "tile_size_x": 2, "tile_size_y": 2, "read_only": 0, "time": 5.151980876922607}, {"block_size_x": 32, "block_size_y": 4, "tile_size_x": 1, "tile_size_y": 4, "read_only": 1, "time": 3.2373055934906008}, {"block_size_x": 64, "block_size_y": 2, "tile_size_x": 2, "tile_size_y": 2, "read_only": 1, "time": 4.121497535705567}, {"block_size_x": 80, "block_size_y": 8, "tile_size_x": 1, "tile_size_y": 3, "read_only": 1, "time": 4.700627136230469}, {"block_size_x": 32, "block_size_y": 8, "tile_size_x": 3, "tile_size_y": 2, "read_only": 0, "time": 5.204089546203614}, {"block_size_x": 64, "block_size_y": 8, "tile_size_x": 1, "tile_size_y": 4, "read_only": 1, "time": 4.300153636932373}, {"block_size_x": 48, "block_size_y": 4, "tile_size_x": 3, "tile_size_y": 1, "read_only": 0, "time": 7.090803146362305}, {"block_size_x": 144, "block_size_y": 2, "tile_size_x": 3, "tile_size_y": 3, "read_only": 1, "time": 7.043129634857178}, {"block_size_x": 96, "block_size_y": 2, "tile_size_x": 3, "tile_size_y": 3, "read_only": 1, "time": 7.024819183349609}, {"block_size_x": 80, "block_size_y": 4, "tile_size_x": 2, "tile_size_y": 4, "read_only": 1, "time": 3.3180095672607424}, {"block_size_x": 128, "block_size_y": 8, "tile_size_x": 2, "tile_size_y": 2, "read_only": 1, "time": 5.4810943603515625}, {"block_size_x": 32, "block_size_y": 2, "tile_size_x": 2, "tile_size_y": 2, "read_only": 0, "time": 4.238540840148926}, {"block_size_x": 32, "block_size_y": 16, "tile_size_x": 3, "tile_size_y": 2, "read_only": 0, "time": 6.726348781585694}, {"block_size_x": 128, "block_size_y": 8, "tile_size_x": 3, "tile_size_y": 1, "read_only": 0, "time": 7.567385578155518}, {"block_size_x": 80, "block_size_y": 8, "tile_size_x": 3, "tile_size_y": 2, "read_only": 0, "time": 5.742316722869873}, {"block_size_x": 16, "block_size_y": 8, "tile_size_x": 3, "tile_size_y": 2, "read_only": 1, "time": 5.059078407287598}, {"block_size_x": 112, "block_size_y": 4, "tile_size_x": 1, "tile_size_y": 3, "read_only": 0, "time": 3.8002431869506834}, {"block_size_x": 112, "block_size_y": 8, "tile_size_x": 2, "tile_size_y": 2, "read_only": 1, "time": 5.668460845947266}, {"block_size_x": 144, "block_size_y": 4, "tile_size_x": 2, "tile_size_y": 3, "read_only": 0, "time": 4.232716846466064}, {"block_size_x": 48, "block_size_y": 2, "tile_size_x": 2, "tile_size_y": 3, "read_only": 1, "time": 3.7879104137420656}, {"block_size_x": 96, "block_size_y": 8, "tile_size_x": 2, "tile_size_y": 3, "read_only": 0, "time": 5.071609592437744}, {"block_size_x": 48, "block_size_y": 8, "tile_size_x": 1, "tile_size_y": 1, "read_only": 1, "time": 6.977433586120606}, {"block_size_x": 48, "block_size_y": 16, "tile_size_x": 1, "tile_size_y": 3, "read_only": 1, "time": 6.757183933258057}, {"block_size_x": 112, "block_size_y": 8, "tile_size_x": 2, "tile_size_y": 4, "read_only": 1, "time": 4.7101696014404295}, {"block_size_x": 16, "block_size_y": 2, "tile_size_x": 2, "tile_size_y": 4, "read_only": 1, "time": 3.7683199882507323}, {"block_size_x": 96, "block_size_y": 8, "tile_size_x": 1, "tile_size_y": 3, "read_only": 1, "time": 4.906137561798095}, {"block_size_x": 16, "block_size_y": 16, "tile_size_x": 2, "tile_size_y": 3, "read_only": 1, "time": 6.515443134307861}, {"block_size_x": 64, "block_size_y": 8, "tile_size_x": 2, "tile_size_y": 3, "read_only": 0, "time": 4.576217460632324}, {"block_size_x": 32, "block_size_y": 8, "tile_size_x": 2, "tile_size_y": 3, "read_only": 0, "time": 4.605068778991699}, {"block_size_x": 64, "block_size_y": 4, "tile_size_x": 1, "tile_size_y": 3, "read_only": 1, "time": 3.66495361328125}, {"block_size_x": 48, "block_size_y": 2, "tile_size_x": 4, "tile_size_y": 3, "read_only": 1, "time": 17.144429016113282}, {"block_size_x": 32, "block_size_y": 4, "tile_size_x": 2, "tile_size_y": 3, "read_only": 0, "time": 3.3079552173614504}, {"block_size_x": 128, "block_size_y": 8, "tile_size_x": 2, "tile_size_y": 3, "read_only": 1, "time": 4.860896015167237}, {"block_size_x": 64, "block_size_y": 8, "tile_size_x": 3, "tile_size_y": 3, "read_only": 1, "time": 7.306579113006592}, {"block_size_x": 48, "block_size_y": 4, "tile_size_x": 2, "tile_size_y": 3, "read_only": 1, "time": 3.701190376281738}, {"block_size_x": 80, "block_size_y": 1, "tile_size_x": 3, "tile_size_y": 3, "read_only": 0, "time": 14.253113555908204}, {"block_size_x": 128, "block_size_y": 8, "tile_size_x": 1, "tile_size_y": 3, "read_only": 1, "time": 4.244108867645264}, {"block_size_x": 256, "block_size_y": 4, "tile_size_x": 1, "tile_size_y": 2, "read_only": 1, "time": 4.156096076965332}, {"block_size_x": 32, "block_size_y": 4, "tile_size_x": 1, "tile_size_y": 1, "read_only": 1, "time": 6.087507152557373}, {"block_size_x": 48, "block_size_y": 8, "tile_size_x": 2, "tile_size_y": 2, "read_only": 1, "time": 4.46999683380127}, {"block_size_x": 96, "block_size_y": 4, "tile_size_x": 1, "tile_size_y": 3, "read_only": 1, "time": 3.2635519981384276}, {"block_size_x": 64, "block_size_y": 8, "tile_size_x": 1, "tile_size_y": 3, "read_only": 1, "time": 3.9978943824768067}, {"block_size_x": 96, "block_size_y": 4, "tile_size_x": 2, "tile_size_y": 4, "read_only": 1, "time": 3.1810688018798827}, {"block_size_x": 128, "block_size_y": 2, "tile_size_x": 3, "tile_size_y": 1, "read_only": 0, "time": 7.795468807220459}, {"block_size_x": 64, "block_size_y": 4, "tile_size_x": 2, "tile_size_y": 3, "read_only": 1, "time": 3.1195647716522217}, {"block_size_x": 64, "block_size_y": 16, "tile_size_x": 1, "tile_size_y": 4, "read_only": 1, "time": 5.772319984436035}, {"block_size_x": 48, "block_size_y": 4, "tile_size_x": 2, "tile_size_y": 1, "read_only": 0, "time": 6.045536041259766}, {"block_size_x": 144, "block_size_y": 2, "tile_size_x": 3, "tile_size_y": 2, "read_only": 0, "time": 6.454521751403808}, {"block_size_x": 32, "block_size_y": 4, "tile_size_x": 3, "tile_size_y": 4, "read_only": 0, "time": 34.96935043334961}, {"block_size_x": 32, "block_size_y": 8, "tile_size_x": 1, "tile_size_y": 3, "read_only": 0, "time": 4.1844159126281735}, {"block_size_x": 80, "block_size_y": 4, "tile_size_x": 2, "tile_size_y": 4, "read_only": 0, "time": 3.0018176078796386}, {"block_size_x": 112, "block_size_y": 8, "tile_size_x": 3, "tile_size_y": 2, "read_only": 1, "time": 5.289292812347412}, {"block_size_x": 32, "block_size_y": 2, "tile_size_x": 3, "tile_size_y": 3, "read_only": 0, "time": 6.118982315063477}, {"block_size_x": 32, "block_size_y": 4, "tile_size_x": 4, "tile_size_y": 2, "read_only": 0, "time": 4.009990406036377}, {"block_size_x": 144, "block_size_y": 4, "tile_size_x": 2, "tile_size_y": 4, "read_only": 0, "time": 3.584870386123657}, {"block_size_x": 160, "block_size_y": 4, "tile_size_x": 2, "tile_size_y": 2, "read_only": 1, "time": 4.322156810760498}, {"block_size_x": 64, "block_size_y": 1, "tile_size_x": 3, "tile_size_y": 1, "read_only": 1, "time": 17.434259033203126}, {"block_size_x": 160, "block_size_y": 4, "tile_size_x": 2, "tile_size_y": 1, "read_only": 0, "time": 6.1632767677307125}, {"block_size_x": 16, "block_size_y": 8, "tile_size_x": 2, "tile_size_y": 4, "read_only": 1, "time": 3.6713536262512205}, {"block_size_x": 48, "block_size_y": 4, "tile_size_x": 3, "tile_size_y": 3, "read_only": 0, "time": 4.129446315765381}]