[{"block_size_x": 128, "block_size_y": 4, "tile_size_x": 2, "tile_size_y": 2, "read_only": 0, "num_streams": 4, "time": 27.418931198120116}, {"block_size_x": 144, "block_size_y": 4, "tile_size_x": 2, "tile_size_y": 2, "read_only": 0, "num_streams": 4, "time": 28.00348815917969}, {"block_size_x": 128, "block_size_y": 8, "tile_size_x": 2, "tile_size_y": 2, "read_only": 0, "num_streams": 4, "time": 27.388672256469725}, {"block_size_x": 128, "block_size_y": 4, "tile_size_x": 2, "tile_size_y": 4, "read_only": 0, "num_streams": 4, "time": 27.12642593383789}, {"block_size_x": 128, "block_size_y": 4, "tile_size_x": 2, "tile_size_y": 2, "read_only": 1, "num_streams": 4, "time": 27.252287673950196}, {"block_size_x": 128, "block_size_y": 4, "tile_size_x": 2, "tile_size_y": 2, "read_only": 0, "num_streams": 8, "time": 27.605197143554687}, {"block_size_x": 128, "block_size_y": 4, "tile_size_x": 1, "tile_size_y": 2, "read_only": 1, "num_streams": 4, "time": 27.64208641052246}, {"block_size_x": 144, "block_size_y": 4, "tile_size_x": 1, "tile_size_y": 2, "read_only": 1, "num_streams": 4, "time": 27.163347244262695}, {"block_size_x": 128, "block_size_y": 8, "tile_size_x": 1, "tile_size_y": 2, "read_only": 1, "num_streams": 4, "time": 27.147250747680665}, {"block_size_x": 128, "block_size_y": 4, "tile_size_x": 1, "tile_size_y": 4, "read_only": 1, "num_streams": 4, "time": 27.134495544433594}, {"block_size_x": 128, "block_size_y": 4, "tile_size_x": 1, "tile_size_y": 2, "read_only": 1, "num_streams": 8, "time": 28.07391357421875}, {"block_size_x": 144, "block_size_y": 4, "tile_size_x": 2, "tile_size_y": 2, "read_only": 1, "num_streams": 4, "time": 26.842719650268556}, {"block_size_x": 128, "block_size_y": 8, "tile_size_x": 2, "tile_size_y": 2, "read_only": 1, "num_streams": 4, "time": 28.17976951599121}, {"block_size_x": 128, "block_size_y": 4, "tile_size_x": 2, "tile_size_y": 4, "read_only": 1, "num_streams": 4, "time": 27.346777725219727}, {"block_size_x": 128, "block_size_y": 4, "tile_size_x": 2, "tile_size_y": 2, "read_only": 1, "num_streams": 8, "time": 27.823942565917967}, {"block_size_x": 128, "block_size_y": 8, "tile_size_x": 1, "tile_size_y": 1, "read_only": 0, "num_streams": 4, "time": 27.182157135009767}, {"block_size_x": 128, "block_size_y": 8, "tile_size_x": 2, "tile_size_y": 1, "read_only": 0, "num_streams": 4, "time": 27.302796936035158}, {"block_size_x": 128, "block_size_y": 8, "tile_size_x": 1, "tile_size_y": 2, "read_only": 0, "num_streams": 4, "time": 27.270771408081053}, {"block_size_x": 128, "block_size_y": 8, "tile_size_x": 1, "tile_size_y": 1, "read_only": 1, "num_streams": 4, "time": 28.01807403564453}, {"block_size_x": 128, "block_size_y": 8, "tile_size_x": 1, "tile_size_y": 1, "read_only": 0, "num_streams": 8, "time": 27.188915634155272}, {"block_size_x": 16, "block_size_y": 1, "tile_size_x": 1, "tile_size_y": 1, "read_only": 0, "num_streams": 4, "time": 27.208550643920898}, {"block_size_x": 16, "block_size_y": 1, "tile_size_x": 2, "tile_size_y": 1, "read_only": 0, "num_streams": 4, "time": 27.458931732177735}, {"block_size_x": 16, "block_size_y": 1, "tile_size_x": 1, "tile_size_y": 2, "read_only": 0, "num_streams": 4, "time": 27.401990509033205}, {"block_size_x": 16, "block_size_y": 1, "tile_size_x": 1, "tile_size_y": 1, "read_only": 1, "num_streams": 4, "time": 27.418585586547852}, {"block_size_x": 16, "block_size_y": 1, "tile_size_x": 1, "tile_size_y": 1, "read_only": 0, "num_streams": 8, "time": 27.95344009399414}, {"block_size_x": 80, "block_size_y": 4, "tile_size_x": 1, "tile_size_y": 1, "read_only": 0, "num_streams": 4, "time": 27.212978744506835}, {"block_size_x": 96, "block_size_y": 4, "tile_size_x": 1, "tile_size_y": 1, "read_only": 0, "num_streams": 4, "time": 28.61727981567383}, {"block_size_x": 80, "block_size_y": 8, "tile_size_x": 1, "tile_size_y": 1, "read_only": 0, "num_streams": 4, "time": 27.14588165283203}, {"block_size_x": 80, "block_size_y": 4, "tile_size_x": 2, "tile_size_y": 1, "read_only": 0, "num_streams": 4, "time": 27.553068923950196}, {"block_size_x": 80, "block_size_y": 4, "tile_size_x": 1, "tile_size_y": 2, "read_only": 0, "num_streams": 4, "time": 27.357856369018556}, {"block_size_x": 80, "block_size_y": 4, "tile_size_x": 1, "tile_size_y": 1, "read_only": 1, "num_streams": 4, "time": 25.94412155151367}, {"block_size_x": 80, "block_size_y": 4, "tile_size_x": 1, "tile_size_y": 1, "read_only": 0, "num_streams": 8, "time": 27.33581428527832}, {"block_size_x": 112, "block_size_y": 8, "tile_size_x": 1, "tile_size_y": 1, "read_only": 0, "num_streams": 4, "time": 27.84030075073242}, {"block_size_x": 112, "block_size_y": 8, "tile_size_x": 2, "tile_size_y": 1, "read_only": 0, "num_streams": 4, "time": 27.221708679199217}, {"block_size_x": 112, "block_size_y": 8, "tile_size_x": 1, "tile_size_y": 2, "read_only": 0, "num_streams": 4, "time": 27.272902297973634}, {"block_size_x": 112, "block_size_y": 8, "tile_size_x": 1, "tile_size_y": 1, "read_only": 1, "num_streams": 4, "time": 27.201395416259764}, {"block_size_x": 112, "block_size_y": 8, "tile_size_x": 1, "tile_size_y": 1, "read_only": 0, "num_streams": 8, "time": 28.57943687438965}, {"block_size_x": 128, "block_size_y": 4, "tile_size_x": 1, "tile_size_y": 1, "read_only": 1, "num_streams": 2, "time": 28.002124786376953}, {"block_size_x": 144, "block_size_y": 4, "tile_size_x": 1, "tile_size_y": 1, "read_only": 1, "num_streams": 2, "time": 28.601849365234376}, {"block_size_x": 128, "block_size_y": 8, "tile_size_x": 1, "tile_size_y": 1, "read_only": 1, "num_streams": 2, "time": 27.706528091430663}, {"block_size_x": 128, "block_size_y": 4, "tile_size_x": 2, "tile_size_y": 1, "read_only": 1, "num_streams": 2, "time": 28.006860733032227}, {"block_size_x": 128, "block_size_y": 4, "tile_size_x": 1, "tile_size_y": 2, "read_only": 1, "num_streams": 2, "time": 28.457798385620116}, {"block_size_x": 128, "block_size_y": 4, "tile_size_x": 1, "tile_size_y": 1, "read_only": 1, "num_streams": 4, "time": 27.43843803405762}, {"block_size_x": 16, "block_size_y": 16, "tile_size_x": 1, "tile_size_y": 1, "read_only": 1, "num_streams": 32, "time": 27.282476806640624}, {"block_size_x": 32, "block_size_y": 16, "tile_size_x": 1, "tile_size_y": 1, "read_only": 1, "num_streams": 32, "time": 27.745862197875976}, {"block_size_x": 16, "block_size_y": 16, "tile_size_x": 2, "tile_size_y": 1, "read_only": 1, "num_streams": 32, "time": 27.291641616821288}, {"block_size_x": 16, "block_size_y": 16, "tile_size_x": 1, "tile_size_y": 2, "read_only": 1, "num_streams": 32, "time": 27.3283203125}, {"block_size_x": 16, "block_size_y": 16, "tile_size_x": 2, "tile_size_y": 2, "read_only": 1, "num_streams": 32, "time": 27.404902267456055}, {"block_size_x": 16, "block_size_y": 16, "tile_size_x": 1, "tile_size_y": 4, "read_only": 1, "num_streams": 32, "time": 27.348089599609374}, {"block_size_x": 16, "block_size_y": 16, "tile_size_x": 1, "tile_size_y": 1, "read_only": 0, "num_streams": 32, "time": 27.393273162841798}, {"block_size_x": 32, "block_size_y": 16, "tile_size_x": 1, "tile_size_y": 1, "read_only": 0, "num_streams": 32, "time": 27.351570892333985}, {"block_size_x": 16, "block_size_y": 16, "tile_size_x": 2, "tile_size_y": 1, "read_only": 0, "num_streams": 32, "time": 27.23222999572754}, {"block_size_x": 48, "block_size_y": 16, "tile_size_x": 1, "tile_size_y": 1, "read_only": 0, "num_streams": 32, "time": 27.39701156616211}, {"block_size_x": 32, "block_size_y": 16, "tile_size_x": 2, "tile_size_y": 1, "read_only": 0, "num_streams": 32, "time": 27.356012725830077}, {"block_size_x": 32, "block_size_y": 16, "tile_size_x": 1, "tile_size_y": 2, "read_only": 0, "num_streams": 32, "time": 24.936857604980467}, {"block_size_x": 16, "block_size_y": 16, "tile_size_x": 1, "tile_size_y": 4, "read_only": 0, "num_streams": 32, "time": 26.17506561279297}, {"block_size_x": 32, "block_size_y": 16, "tile_size_x": 1, "tile_size_y": 4, "read_only": 0, "num_streams": 32, "time": 27.123411178588867}, {"block_size_x": 48, "block_size_y": 16, "tile_size_x": 1, "tile_size_y": 4, "read_only": 0, "num_streams": 32, "time": 25.44499855041504}, {"block_size_x": 32, "block_size_y": 16, "tile_size_x": 2, "tile_size_y": 4, "read_only": 0, "num_streams": 32, "time": 27.491955184936522}, {"block_size_x": 32, "block_size_y": 16, "tile_size_x": 1, "tile_size_y": 4, "read_only": 1, "num_streams": 32, "time": 27.361356353759767}, {"block_size_x": 16, "block_size_y": 8, "tile_size_x": 1, "tile_size_y": 4, "read_only": 0, "num_streams": 32, "time": 27.38433265686035}, {"block_size_x": 32, "block_size_y": 8, "tile_size_x": 1, "tile_size_y": 4, "read_only": 0, "num_streams": 32, "time": 27.63459167480469}, {"block_size_x": 16, "block_size_y": 8, "tile_size_x": 2, "tile_size_y": 4, "read_only": 0, "num_streams": 32, "time": 26.542668914794923}, {"block_size_x": 16, "block_size_y": 8, "tile_size_x": 1, "tile_size_y": 4, "read_only": 1, "num_streams": 32, "time": 27.253311920166016}, {"block_size_x": 16, "block_size_y": 16, "tile_size_x": 4, "tile_size_y": 4, "read_only": 1, "num_streams": 32, "time": 27.579021072387697}, {"block_size_x": 16, "block_size_y": 16, "tile_size_x": 2, "tile_size_y": 4, "read_only": 0, "num_streams": 32, "time": 27.4446533203125}, {"block_size_x": 16, "block_size_y": 16, "tile_size_x": 1, "tile_size_y": 4, "read_only": 0, "num_streams": 16, "time": 27.2380729675293}, {"block_size_x": 16, "block_size_y": 16, "tile_size_x": 2, "tile_size_y": 4, "read_only": 0, "num_streams": 16, "time": 26.05235176086426}, {"block_size_x": 16, "block_size_y": 16, "tile_size_x": 1, "tile_size_y": 4, "read_only": 1, "num_streams": 16, "time": 27.340678024291993}, {"block_size_x": 16, "block_size_y": 16, "tile_size_x": 4, "tile_size_y": 4, "read_only": 0, "num_streams": 32, "time": 26.19075164794922}, {"block_size_x": 16, "block_size_y": 16, "tile_size_x": 4, "tile_size_y": 4, "read_only": 0, "num_streams": 16, "time": 24.329056167602538}, {"block_size_x": 16, "block_size_y": 16, "tile_size_x": 4, "tile_size_y": 4, "read_only": 1, "num_streams": 16, "time": 27.071757125854493}, {"block_size_x": 16, "block_size_y": 16, "tile_size_x": 4, "tile_size_y": 2, "read_only": 1, "num_streams": 16, "time": 28.152416229248047}, {"block_size_x": 32, "block_size_y": 16, "tile_size_x": 4, "tile_size_y": 2, "read_only": 1, "num_streams": 16, "time": 28.05770263671875}, {"block_size_x": 16, "block_size_y": 16, "tile_size_x": 4, "tile_size_y": 2, "read_only": 1, "num_streams": 32, "time": 27.52620162963867}, {"block_size_x": 16, "block_size_y": 16, "tile_size_x": 4, "tile_size_y": 4, "read_only": 1, "num_streams": 8, "time": 26.01591682434082}, {"block_size_x": 16, "block_size_y": 16, "tile_size_x": 4, "tile_size_y": 4, "read_only": 0, "num_streams": 8, "time": 27.60555534362793}, {"block_size_x": 16, "block_size_y": 16, "tile_size_x": 4, "tile_size_y": 4, "read_only": 0, "num_streams": 1, "time": 42.45756149291992}, {"block_size_x": 16, "block_size_y": 16, "tile_size_x": 4, "tile_size_y": 4, "read_only": 1, "num_streams": 1, "time": 41.607968139648435}, {"block_size_x": 16, "block_size_y": 16, "tile_size_x": 4, "tile_size_y": 2, "read_only": 0, "num_streams": 16, "time": 27.014022064208984}, {"block_size_x": 16, "block_size_y": 16, "tile_size_x": 4, "tile_size_y": 2, "read_only": 0, "num_streams": 32, "time": 27.40460777282715}, {"block_size_x": 32, "block_size_y": 16, "tile_size_x": 4, "tile_size_y": 2, "read_only": 0, "num_streams": 16, "time": 27.43944969177246}, {"block_size_x": 16, "block_size_y": 16, "tile_size_x": 4, "tile_size_y": 4, "read_only": 0, "num_streams": 4, "time": 25.86588821411133}, {"block_size_x": 16, "block_size_y": 16, "tile_size_x": 4, "tile_size_y": 4, "read_only": 1, "num_streams": 4, "time": 28.074118423461915}, {"block_size_x": 16, "block_size_y": 16, "tile_size_x": 4, "tile_size_y": 2, "read_only": 0, "num_streams": 8, "time": 27.417522811889647}, {"block_size_x": 16, "block_size_y": 16, "tile_size_x": 4, "tile_size_y": 2, "read_only": 1, "num_streams": 8, "time": 27.2968318939209}, {"block_size_x": 16, "block_size_y": 16, "tile_size_x": 4, "tile_size_y": 1, "read_only": 1, "num_streams": 32, "time": 26.75169906616211}, {"block_size_x": 32, "block_size_y": 16, "tile_size_x": 4, "tile_size_y": 2, "read_only": 0, "num_streams": 8, "time": 27.61270408630371}, {"block_size_x": 16, "block_size_y": 16, "tile_size_x": 2, "tile_size_y": 4, "read_only": 1, "num_streams": 32, "time": 28.28134422302246}, {"block_size_x": 16, "block_size_y": 8, "tile_size_x": 4, "tile_size_y": 4, "read_only": 0, "num_streams": 32, "time": 94.62552337646484}, {"block_size_x": 16, "block_size_y": 8, "tile_size_x": 4, "tile_size_y": 4, "read_only": 1, "num_streams": 32, "time": 94.46787719726562}, {"block_size_x": 32, "block_size_y": 8, "tile_size_x": 4, "tile_size_y": 4, "read_only": 1, "num_streams": 32, "time": 92.69841766357422}, {"block_size_x": 16, "block_size_y": 8, "tile_size_x": 2, "tile_size_y": 4, "read_only": 1, "num_streams": 32, "time": 27.315705490112304}, {"block_size_x": 16, "block_size_y": 1, "tile_size_x": 1, "tile_size_y": 4, "read_only": 1, "num_streams": 32, "time": 28.214144897460937}, {"block_size_x": 16, "block_size_y": 4, "tile_size_x": 2, "tile_size_y": 4, "read_only": 1, "num_streams": 32, "time": 27.195475006103514}, {"block_size_x": 16, "block_size_y": 4, "tile_size_x": 4, "tile_size_y": 4, "read_only": 1, "num_streams": 32, "time": 75.13126983642579}, {"block_size_x": 16, "block_size_y": 2, "tile_size_x": 1, "tile_size_y": 4, "read_only": 1, "num_streams": 32, "time": 27.219507217407227}, {"block_size_x": 16, "block_size_y": 4, "tile_size_x": 1, "tile_size_y": 4, "read_only": 1, "num_streams": 32, "time": 26.81091194152832}, {"block_size_x": 16, "block_size_y": 2, "tile_size_x": 2, "tile_size_y": 4, "read_only": 1, "num_streams": 32, "time": 24.51033592224121}, {"block_size_x": 32, "block_size_y": 8, "tile_size_x": 4, "tile_size_y": 4, "read_only": 0, "num_streams": 32, "time": 92.81629638671875}, {"block_size_x": 32, "block_size_y": 16, "tile_size_x": 2, "tile_size_y": 4, "read_only": 1, "num_streams": 16, "time": 27.529357147216796}, {"block_size_x": 32, "block_size_y": 16, "tile_size_x": 2, "tile_size_y": 4, "read_only": 1, "num_streams": 32, "time": 27.679136276245117}, {"block_size_x": 16, "block_size_y": 16, "tile_size_x": 2, "tile_size_y": 4, "read_only": 1, "num_streams": 16, "time": 27.408870697021484}, {"block_size_x": 32, "block_size_y": 16, "tile_size_x": 2, "tile_size_y": 2, "read_only": 0, "num_streams": 16, "time": 27.510156631469727}, {"block_size_x": 48, "block_size_y": 16, "tile_size_x": 2, "tile_size_y": 2, "read_only": 0, "num_streams": 16, "time": 27.25294075012207}, {"block_size_x": 32, "block_size_y": 16, "tile_size_x": 2, "tile_size_y": 4, "read_only": 0, "num_streams": 16, "time": 24.10423698425293}, {"block_size_x": 32, "block_size_y": 16, "tile_size_x": 2, "tile_size_y": 2, "read_only": 1, "num_streams": 16, "time": 27.338169479370116}, {"block_size_x": 32, "block_size_y": 16, "tile_size_x": 2, "tile_size_y": 2, "read_only": 0, "num_streams": 32, "time": 27.464736557006837}, {"block_size_x": 16, "block_size_y": 16, "tile_size_x": 2, "tile_size_y": 2, "read_only": 0, "num_streams": 16, "time": 27.407693099975585}, {"block_size_x": 16, "block_size_y": 16, "tile_size_x": 2, "tile_size_y": 2, "read_only": 1, "num_streams": 16, "time": 26.14044189453125}, {"block_size_x": 16, "block_size_y": 16, "tile_size_x": 2, "tile_size_y": 2, "read_only": 0, "num_streams": 32, "time": 27.561222076416016}, {"block_size_x": 16, "block_size_y": 16, "tile_size_x": 2, "tile_size_y": 1, "read_only": 1, "num_streams": 16, "time": 27.16506881713867}, {"block_size_x": 16, "block_size_y": 16, "tile_size_x": 4, "tile_size_y": 1, "read_only": 1, "num_streams": 16, "time": 27.733100509643556}, {"block_size_x": 16, "block_size_y": 16, "tile_size_x": 1, "tile_size_y": 4, "read_only": 1, "num_streams": 1, "time": 36.0312255859375}, {"block_size_x": 16, "block_size_y": 16, "tile_size_x": 1, "tile_size_y": 4, "read_only": 1, "num_streams": 4, "time": 28.07009925842285}, {"block_size_x": 16, "block_size_y": 16, "tile_size_x": 2, "tile_size_y": 4, "read_only": 1, "num_streams": 4, "time": 27.550284576416015}, {"block_size_x": 16, "block_size_y": 16, "tile_size_x": 1, "tile_size_y": 4, "read_only": 1, "num_streams": 8, "time": 26.398105239868165}, {"block_size_x": 16, "block_size_y": 16, "tile_size_x": 2, "tile_size_y": 2, "read_only": 1, "num_streams": 8, "time": 25.51095657348633}, {"block_size_x": 16, "block_size_y": 16, "tile_size_x": 2, "tile_size_y": 4, "read_only": 1, "num_streams": 8, "time": 27.62884521484375}, {"block_size_x": 16, "block_size_y": 16, "tile_size_x": 1, "tile_size_y": 4, "read_only": 1, "num_streams": 2, "time": 26.911731338500978}, {"block_size_x": 16, "block_size_y": 16, "tile_size_x": 2, "tile_size_y": 4, "read_only": 1, "num_streams": 2, "time": 28.48782730102539}, {"block_size_x": 16, "block_size_y": 16, "tile_size_x": 1, "tile_size_y": 1, "read_only": 1, "num_streams": 1, "time": 36.24582366943359}, {"block_size_x": 16, "block_size_y": 8, "tile_size_x": 1, "tile_size_y": 4, "read_only": 1, "num_streams": 8, "time": 26.58495330810547}, {"block_size_x": 16, "block_size_y": 8, "tile_size_x": 2, "tile_size_y": 4, "read_only": 1, "num_streams": 8, "time": 27.22154884338379}, {"block_size_x": 16, "block_size_y": 8, "tile_size_x": 1, "tile_size_y": 4, "read_only": 1, "num_streams": 16, "time": 24.688313674926757}, {"block_size_x": 16, "block_size_y": 16, "tile_size_x": 1, "tile_size_y": 2, "read_only": 0, "num_streams": 8, "time": 27.301465225219726}, {"block_size_x": 32, "block_size_y": 16, "tile_size_x": 1, "tile_size_y": 2, "read_only": 0, "num_streams": 8, "time": 27.257215881347655}, {"block_size_x": 16, "block_size_y": 16, "tile_size_x": 2, "tile_size_y": 2, "read_only": 0, "num_streams": 8, "time": 26.58899841308594}, {"block_size_x": 16, "block_size_y": 16, "tile_size_x": 1, "tile_size_y": 4, "read_only": 0, "num_streams": 8, "time": 25.064038467407226}, {"block_size_x": 16, "block_size_y": 16, "tile_size_x": 1, "tile_size_y": 2, "read_only": 1, "num_streams": 8, "time": 27.58886375427246}, {"block_size_x": 16, "block_size_y": 16, "tile_size_x": 1, "tile_size_y": 2, "read_only": 0, "num_streams": 16, "time": 26.062175750732422}, {"block_size_x": 16, "block_size_y": 8, "tile_size_x": 2, "tile_size_y": 2, "read_only": 1, "num_streams": 8, "time": 27.24535026550293}, {"block_size_x": 16, "block_size_y": 8, "tile_size_x": 4, "tile_size_y": 2, "read_only": 1, "num_streams": 8, "time": 26.36391677856445}, {"block_size_x": 16, "block_size_y": 8, "tile_size_x": 2, "tile_size_y": 2, "read_only": 1, "num_streams": 16, "time": 27.371712493896485}, {"block_size_x": 16, "block_size_y": 8, "tile_size_x": 4, "tile_size_y": 2, "read_only": 0, "num_streams": 16, "time": 27.15202522277832}, {"block_size_x": 32, "block_size_y": 8, "tile_size_x": 4, "tile_size_y": 2, "read_only": 0, "num_streams": 16, "time": 27.239782333374023}, {"block_size_x": 16, "block_size_y": 8, "tile_size_x": 4, "tile_size_y": 4, "read_only": 0, "num_streams": 16, "time": 96.52158660888672}, {"block_size_x": 16, "block_size_y": 8, "tile_size_x": 4, "tile_size_y": 2, "read_only": 1, "num_streams": 16, "time": 27.453676223754883}, {"block_size_x": 16, "block_size_y": 8, "tile_size_x": 4, "tile_size_y": 2, "read_only": 0, "num_streams": 32, "time": 24.236928176879882}, {"block_size_x": 16, "block_size_y": 16, "tile_size_x": 4, "tile_size_y": 1, "read_only": 0, "num_streams": 32, "time": 27.40511360168457}, {"block_size_x": 16, "block_size_y": 8, "tile_size_x": 2, "tile_size_y": 2, "read_only": 0, "num_streams": 32, "time": 27.623366165161134}, {"block_size_x": 16, "block_size_y": 8, "tile_size_x": 2, "tile_size_y": 2, "read_only": 1, "num_streams": 32, "time": 26.728160095214843}, {"block_size_x": 16, "block_size_y": 16, "tile_size_x": 4, "tile_size_y": 4, "read_only": 0, "num_streams": 2, "time": 29.244300842285156}, {"block_size_x": 16, "block_size_y": 16, "tile_size_x": 4, "tile_size_y": 4, "read_only": 1, "num_streams": 2, "time": 29.250317001342772}, {"block_size_x": 32, "block_size_y": 16, "tile_size_x": 2, "tile_size_y": 4, "read_only": 1, "num_streams": 8, "time": 27.230713653564454}, {"block_size_x": 48, "block_size_y": 8, "tile_size_x": 1, "tile_size_y": 4, "read_only": 0, "num_streams": 32, "time": 27.284653091430663}, {"block_size_x": 32, "block_size_y": 8, "tile_size_x": 2, "tile_size_y": 4, "read_only": 0, "num_streams": 32, "time": 27.356505584716796}]