[{"MWG": 32, "NWG": 32, "KWG": 32, "MDIMC": 16, "NDIMC": 16, "MDIMA": 16, "NDIMB": 16, "KWI": 2, "VWM": 2, "VWN": 2, "STRM": 0, "STRN": 0, "SA": 0, "SB": 0, "PRECISION": 32, "time": 19.956499200000003}, {"MWG": 64, "NWG": 32, "KWG": 32, "MDIMC": 16, "NDIMC": 16, "MDIMA": 16, "NDIMB": 16, "KWI": 2, "VWM": 2, "VWN": 2, "STRM": 0, "STRN": 0, "SA": 0, "SB": 0, "PRECISION": 32, "time": 23.7912064}, {"MWG": 32, "NWG": 64, "KWG": 32, "MDIMC": 16, "NDIMC": 16, "MDIMA": 16, "NDIMB": 16, "KWI": 2, "VWM": 2, "VWN": 2, "STRM": 0, "STRN": 0, "SA": 0, "SB": 0, "PRECISION": 32, "time": 15.116883199999998}, {"MWG": 32, "NWG": 32, "KWG": 32, "MDIMC": 16, "NDIMC": 16, "MDIMA": 16, "NDIMB": 16, "KWI": 2, "VWM": 2, "VWN": 2, "STRM": 0, "STRN": 0, "SA": 1, "SB": 0, "PRECISION": 32, "time": 10.801260800000001}, {"MWG": 32, "NWG": 32, "KWG": 32, "MDIMC": 16, "NDIMC": 16, "MDIMA": 16, "NDIMB": 16, "KWI": 2, "VWM": 2, "VWN": 2, "STRM": 0, "STRN": 0, "SA": 0, "SB": 1, "PRECISION": 32, "time": 10.7619072}, {"MWG": 32, "NWG": 32, "KWG": 32, "MDIMC": 8, "NDIMC": 8, "MDIMA": 8, "NDIMB": 8, "KWI": 2, "VWM": 1, "VWN": 1, "STRM": 0, "STRN": 0, "SA": 0, "SB": 0, "PRECISION": 32, "time": 16.4646144}, {"MWG": 64, "NWG": 32, "KWG": 32, "MDIMC": 8, "NDIMC": 8, "MDIMA": 8, "NDIMB": 8, "KWI": 2, "VWM": 1, "VWN": 1, "STRM": 0, "STRN": 0, "SA": 0, "SB": 0, "PRECISION": 32, "time": 8.332524799999998}, {"MWG": 32, "NWG": 64, "KWG": 32, "MDIMC": 8, "NDIMC": 8, "MDIMA": 8, "NDIMB": 8, "KWI": 2, "VWM": 1, "VWN": 1, "STRM": 0, "STRN": 0, "SA": 0, "SB": 0, "PRECISION": 32, "time": 12.9788672}, {"MWG": 32, "NWG": 32, "KWG": 32, "MDIMC": 16, "NDIMC": 8, "MDIMA": 8, "NDIMB": 8, "KWI": 2, "VWM": 1, "VWN": 1, "STRM": 0, "STRN": 0, "SA": 0, "SB": 0, "PRECISION": 32, "time": 15.399558399999998}, {"MWG": 32, "NWG": 32, "KWG": 32, "MDIMC": 8, "NDIMC": 16, "MDIMA": 8, "NDIMB": 8, "KWI": 2, "VWM": 1, "VWN": 1, "STRM": 0, "STRN": 0, "SA": 0, "SB": 0, "PRECISION": 32, "time": 24.8811712}, {"MWG": 32, "NWG": 32, "KWG": 32, "MDIMC": 8, "NDIMC": 8, "MDIMA": 16, "NDIMB": 8, "KWI": 2, "VWM": 1, "VWN": 1, "STRM": 0, "STRN": 0, "SA": 0, "SB": 0, "PRECISION": 32, "time": 16.4683136}, {"MWG": 32, "NWG": 32, "KWG": 32, "MDIMC": 8, "NDIMC": 8, "MDIMA": 8, "NDIMB": 16, "KWI": 2, "VWM": 1, "VWN": 1, "STRM": 0, "STRN": 0, "SA": 0, "SB": 0, "PRECISION": 32, "time": 16.463456}, {"MWG": 32, "NWG": 32, "KWG": 32, "MDIMC": 8, "NDIMC": 8, "MDIMA": 8, "NDIMB": 8, "KWI": 2, "VWM": 2, "VWN": 1, "STRM": 0, "STRN": 0, "SA": 0, "SB": 0, "PRECISION": 32, "time": 10.7862336}, {"MWG": 32, "NWG": 32, "KWG": 32, "MDIMC": 8, "NDIMC": 8, "MDIMA": 8, "NDIMB": 8, "KWI": 2, "VWM": 1, "VWN": 2, "STRM": 0, "STRN": 0, "SA": 0, "SB": 0, "PRECISION": 32, "time": 15.020281599999999}, {"MWG": 32, "NWG": 32, "KWG": 32, "MDIMC": 8, "NDIMC": 8, "MDIMA": 8, "NDIMB": 8, "KWI": 2, "VWM": 1, "VWN": 1, "STRM": 0, "STRN": 0, "SA": 1, "SB": 0, "PRECISION": 32, "time": 7.839641599999998}, {"MWG": 32, "NWG": 32, "KWG": 32, "MDIMC": 8, "NDIMC": 8, "MDIMA": 8, "NDIMB": 8, "KWI": 2, "VWM": 1, "VWN": 1, "STRM": 0, "STRN": 0, "SA": 0, "SB": 1, "PRECISION": 32, "time": 12.575257599999997}]