[{"MWG": 32, "NWG": 32, "KWG": 32, "MDIMC": 16, "NDIMC": 16, "MDIMA": 8, "NDIMB": 16, "KWI": 2, "VWM": 2, "VWN": 1, "STRM": 0, "STRN": 0, "SA": 1, "SB": 1, "PRECISION": 32, "time": 11.0060672}, {"MWG": 32, "NWG": 32, "KWG": 32, "MDIMC": 16, "NDIMC": 16, "MDIMA": 16, "NDIMB": 16, "KWI": 2, "VWM": 1, "VWN": 1, "STRM": 0, "STRN": 0, "SA": 1, "SB": 0, "PRECISION": 32, "time": 11.7387136}, {"MWG": 64, "NWG": 64, "KWG": 32, "MDIMC": 16, "NDIMC": 16, "MDIMA": 32, "NDIMB": 16, "KWI": 2, "VWM": 1, "VWN": 2, "STRM": 0, "STRN": 0, "SA": 0, "SB": 1, "PRECISION": 32, "time": 21.5346624}, {"MWG": 32, "NWG": 32, "KWG": 32, "MDIMC": 32, "NDIMC": 16, "MDIMA": 32, "NDIMB": 16, "KWI": 2, "VWM": 1, "VWN": 2, "STRM": 0, "STRN": 0, "SA": 0, "SB": 0, "PRECISION": 32, "time": 30.248038400000002}, {"MWG": 32, "NWG": 32, "KWG": 32, "MDIMC": 32, "NDIMC": 16, "MDIMA": 32, "NDIMB": 32, "KWI": 2, "VWM": 1, "VWN": 1, "STRM": 0, "STRN": 0, "SA": 1, "SB": 0, "PRECISION": 32, "time": 30.117881599999997}, {"MWG": 64, "NWG": 64, "KWG": 32, "MDIMC": 16, "NDIMC": 8, "MDIMA": 16, "NDIMB": 32, "KWI": 2, "VWM": 2, "VWN": 1, "STRM": 0, "STRN": 0, "SA": 0, "SB": 1, "PRECISION": 32, "time": 6.3797376}, {"MWG": 32, "NWG": 32, "KWG": 32, "MDIMC": 16, "NDIMC": 16, "MDIMA": 8, "NDIMB": 16, "KWI": 2, "VWM": 2, "VWN": 2, "STRM": 0, "STRN": 0, "SA": 0, "SB": 1, "PRECISION": 32, "time": 11.031596799999999}, {"MWG": 32, "NWG": 64, "KWG": 32, "MDIMC": 16, "NDIMC": 16, "MDIMA": 8, "NDIMB": 16, "KWI": 2, "VWM": 1, "VWN": 2, "STRM": 0, "STRN": 0, "SA": 1, "SB": 1, "PRECISION": 32, "time": 6.7176896}, {"MWG": 16, "NWG": 64, "KWG": 32, "MDIMC": 16, "NDIMC": 16, "MDIMA": 16, "NDIMB": 16, "KWI": 2, "VWM": 1, "VWN": 4, "STRM": 0, "STRN": 0, "SA": 1, "SB": 0, "PRECISION": 32, "time": 20.681299199999998}, {"MWG": 32, "NWG": 64, "KWG": 32, "MDIMC": 16, "NDIMC": 16, "MDIMA": 16, "NDIMB": 32, "KWI": 2, "VWM": 1, "VWN": 2, "STRM": 0, "STRN": 0, "SA": 0, "SB": 1, "PRECISION": 32, "time": 7.350950399999999}, {"MWG": 64, "NWG": 64, "KWG": 32, "MDIMC": 32, "NDIMC": 8, "MDIMA": 32, "NDIMB": 16, "KWI": 2, "VWM": 2, "VWN": 2, "STRM": 0, "STRN": 0, "SA": 1, "SB": 0, "PRECISION": 32, "time": 10.8499136}, {"MWG": 32, "NWG": 64, "KWG": 32, "MDIMC": 8, "NDIMC": 32, "MDIMA": 8, "NDIMB": 16, "KWI": 2, "VWM": 2, "VWN": 2, "STRM": 0, "STRN": 0, "SA": 1, "SB": 0, "PRECISION": 32, "time": 6.5472063999999985}, {"MWG": 64, "NWG": 32, "KWG": 32, "MDIMC": 16, "NDIMC": 32, "MDIMA": 32, "NDIMB": 32, "KWI": 2, "VWM": 1, "VWN": 1, "STRM": 0, "STRN": 0, "SA": 0, "SB": 1, "PRECISION": 32, "time": 79.0352576}, {"MWG": 64, "NWG": 64, "KWG": 32, "MDIMC": 16, "NDIMC": 32, "MDIMA": 16, "NDIMB": 32, "KWI": 2, "VWM": 2, "VWN": 2, "STRM": 0, "STRN": 0, "SA": 1, "SB": 0, "PRECISION": 32, "time": 10.773958399999998}, {"MWG": 64, "NWG": 32, "KWG": 32, "MDIMC": 16, "NDIMC": 16, "MDIMA": 32, "NDIMB": 8, "KWI": 2, "VWM": 1, "VWN": 2, "STRM": 0, "STRN": 0, "SA": 1, "SB": 1, "PRECISION": 32, "time": 12.52464}, {"MWG": 32, "NWG": 32, "KWG": 32, "MDIMC": 16, "NDIMC": 8, "MDIMA": 16, "NDIMB": 16, "KWI": 2, "VWM": 2, "VWN": 1, "STRM": 0, "STRN": 0, "SA": 1, "SB": 0, "PRECISION": 32, "time": 11.561164799999997}, {"MWG": 64, "NWG": 32, "KWG": 32, "MDIMC": 16, "NDIMC": 16, "MDIMA": 16, "NDIMB": 16, "KWI": 2, "VWM": 2, "VWN": 2, "STRM": 0, "STRN": 0, "SA": 0, "SB": 1, "PRECISION": 32, "time": 20.673171200000002}, {"MWG": 32, "NWG": 64, "KWG": 32, "MDIMC": 8, "NDIMC": 16, "MDIMA": 16, "NDIMB": 16, "KWI": 2, "VWM": 2, "VWN": 1, "STRM": 0, "STRN": 0, "SA": 1, "SB": 1, "PRECISION": 32, "time": 5.063295999999999}, {"MWG": 64, "NWG": 32, "KWG": 32, "MDIMC": 16, "NDIMC": 16, "MDIMA": 8, "NDIMB": 16, "KWI": 2, "VWM": 2, "VWN": 1, "STRM": 0, "STRN": 0, "SA": 0, "SB": 0, "PRECISION": 32, "time": 26.1782208}, {"MWG": 32, "NWG": 64, "KWG": 32, "MDIMC": 16, "NDIMC": 32, "MDIMA": 32, "NDIMB": 16, "KWI": 2, "VWM": 1, "VWN": 2, "STRM": 0, "STRN": 0, "SA": 0, "SB": 1, "PRECISION": 32, "time": 12.4760064}, {"MWG": 64, "NWG": 64, "KWG": 32, "MDIMC": 8, "NDIMC": 32, "MDIMA": 32, "NDIMB": 16, "KWI": 2, "VWM": 1, "VWN": 2, "STRM": 0, "STRN": 0, "SA": 0, "SB": 0, "PRECISION": 32, "time": 13.413695999999998}, {"MWG": 32, "NWG": 64, "KWG": 32, "MDIMC": 16, "NDIMC": 8, "MDIMA": 16, "NDIMB": 8, "KWI": 2, "VWM": 2, "VWN": 4, "STRM": 0, "STRN": 0, "SA": 0, "SB": 1, "PRECISION": 32, "time": 4.494963199999999}, {"MWG": 64, "NWG": 32, "KWG": 32, "MDIMC": 16, "NDIMC": 8, "MDIMA": 8, "NDIMB": 16, "KWI": 2, "VWM": 1, "VWN": 1, "STRM": 0, "STRN": 0, "SA": 1, "SB": 0, "PRECISION": 32, "time": 7.072217599999999}, {"MWG": 64, "NWG": 64, "KWG": 32, "MDIMC": 8, "NDIMC": 16, "MDIMA": 16, "NDIMB": 32, "KWI": 2, "VWM": 2, "VWN": 2, "STRM": 0, "STRN": 0, "SA": 1, "SB": 0, "PRECISION": 32, "time": 6.2338048}, {"MWG": 32, "NWG": 32, "KWG": 32, "MDIMC": 8, "NDIMC": 8, "MDIMA": 16, "NDIMB": 32, "KWI": 2, "VWM": 2, "VWN": 1, "STRM": 0, "STRN": 0, "SA": 1, "SB": 1, "PRECISION": 32, "time": 5.1516608}, {"MWG": 32, "NWG": 32, "KWG": 32, "MDIMC": 16, "NDIMC": 16, "MDIMA": 32, "NDIMB": 8, "KWI": 2, "VWM": 1, "VWN": 2, "STRM": 0, "STRN": 0, "SA": 1, "SB": 1, "PRECISION": 32, "time": 9.090335999999999}, {"MWG": 64, "NWG": 64, "KWG": 32, "MDIMC": 16, "NDIMC": 16, "MDIMA": 16, "NDIMB": 8, "KWI": 2, "VWM": 2, "VWN": 2, "STRM": 0, "STRN": 0, "SA": 0, "SB": 1, "PRECISION": 32, "time": 11.181651200000001}, {"MWG": 64, "NWG": 64, "KWG": 32, "MDIMC": 16, "NDIMC": 8, "MDIMA": 32, "NDIMB": 32, "KWI": 2, "VWM": 2, "VWN": 1, "STRM": 0, "STRN": 0, "SA": 0, "SB": 1, "PRECISION": 32, "time": 6.3641472}, {"MWG": 32, "NWG": 32, "KWG": 32, "MDIMC": 16, "NDIMC": 16, "MDIMA": 16, "NDIMB": 16, "KWI": 2, "VWM": 2, "VWN": 2, "STRM": 0, "STRN": 0, "SA": 1, "SB": 0, "PRECISION": 32, "time": 11.0407616}, {"MWG": 64, "NWG": 32, "KWG": 32, "MDIMC": 16, "NDIMC": 8, "MDIMA": 16, "NDIMB": 8, "KWI": 2, "VWM": 4, "VWN": 1, "STRM": 0, "STRN": 0, "SA": 1, "SB": 1, "PRECISION": 32, "time": 5.056928}, {"MWG": 64, "NWG": 64, "KWG": 32, "MDIMC": 16, "NDIMC": 32, "MDIMA": 32, "NDIMB": 32, "KWI": 2, "VWM": 2, "VWN": 2, "STRM": 0, "STRN": 0, "SA": 1, "SB": 0, "PRECISION": 32, "time": 10.613792}, {"MWG": 64, "NWG": 64, "KWG": 32, "MDIMC": 8, "NDIMC": 8, "MDIMA": 16, "NDIMB": 16, "KWI": 2, "VWM": 4, "VWN": 4, "STRM": 0, "STRN": 0, "SA": 0, "SB": 0, "PRECISION": 32, "time": 5.853631999999999}, {"MWG": 64, "NWG": 64, "KWG": 32, "MDIMC": 8, "NDIMC": 16, "MDIMA": 16, "NDIMB": 32, "KWI": 2, "VWM": 2, "VWN": 2, "STRM": 0, "STRN": 0, "SA": 0, "SB": 1, "PRECISION": 32, "time": 7.1387136}, {"MWG": 64, "NWG": 32, "KWG": 32, "MDIMC": 32, "NDIMC": 8, "MDIMA": 16, "NDIMB": 8, "KWI": 2, "VWM": 1, "VWN": 2, "STRM": 0, "STRN": 0, "SA": 1, "SB": 0, "PRECISION": 32, "time": 12.62688}, {"MWG": 64, "NWG": 64, "KWG": 32, "MDIMC": 8, "NDIMC": 32, "MDIMA": 16, "NDIMB": 8, "KWI": 2, "VWM": 2, "VWN": 2, "STRM": 0, "STRN": 0, "SA": 1, "SB": 0, "PRECISION": 32, "time": 10.9260672}, {"MWG": 64, "NWG": 64, "KWG": 32, "MDIMC": 8, "NDIMC": 16, "MDIMA": 8, "NDIMB": 32, "KWI": 2, "VWM": 2, "VWN": 2, "STRM": 0, "STRN": 0, "SA": 0, "SB": 1, "PRECISION": 32, "time": 7.1596992}, {"MWG": 32, "NWG": 64, "KWG": 32, "MDIMC": 16, "NDIMC": 16, "MDIMA": 8, "NDIMB": 8, "KWI": 2, "VWM": 2, "VWN": 1, "STRM": 0, "STRN": 0, "SA": 0, "SB": 1, "PRECISION": 32, "time": 7.138867199999998}, {"MWG": 32, "NWG": 32, "KWG": 32, "MDIMC": 16, "NDIMC": 8, "MDIMA": 16, "NDIMB": 16, "KWI": 2, "VWM": 2, "VWN": 2, "STRM": 0, "STRN": 0, "SA": 0, "SB": 0, "PRECISION": 32, "time": 15.455315200000001}, {"MWG": 32, "NWG": 64, "KWG": 32, "MDIMC": 32, "NDIMC": 16, "MDIMA": 32, "NDIMB": 16, "KWI": 2, "VWM": 1, "VWN": 2, "STRM": 0, "STRN": 0, "SA": 1, "SB": 1, "PRECISION": 32, "time": 9.2092736}, {"MWG": 32, "NWG": 64, "KWG": 32, "MDIMC": 8, "NDIMC": 32, "MDIMA": 16, "NDIMB": 16, "KWI": 2, "VWM": 2, "VWN": 2, "STRM": 0, "STRN": 0, "SA": 1, "SB": 0, "PRECISION": 32, "time": 6.389523200000001}, {"MWG": 32, "NWG": 64, "KWG": 32, "MDIMC": 8, "NDIMC": 32, "MDIMA": 16, "NDIMB": 16, "KWI": 2, "VWM": 2, "VWN": 2, "STRM": 0, "STRN": 0, "SA": 0, "SB": 0, "PRECISION": 32, "time": 15.468633599999999}, {"MWG": 32, "NWG": 64, "KWG": 32, "MDIMC": 32, "NDIMC": 16, "MDIMA": 32, "NDIMB": 16, "KWI": 2, "VWM": 1, "VWN": 2, "STRM": 0, "STRN": 0, "SA": 0, "SB": 0, "PRECISION": 32, "time": 25.5766656}, {"MWG": 32, "NWG": 64, "KWG": 32, "MDIMC": 16, "NDIMC": 16, "MDIMA": 16, "NDIMB": 32, "KWI": 2, "VWM": 2, "VWN": 2, "STRM": 0, "STRN": 0, "SA": 1, "SB": 0, "PRECISION": 32, "time": 10.6876992}, {"MWG": 64, "NWG": 32, "KWG": 32, "MDIMC": 16, "NDIMC": 16, "MDIMA": 16, "NDIMB": 16, "KWI": 2, "VWM": 2, "VWN": 2, "STRM": 0, "STRN": 0, "SA": 1, "SB": 0, "PRECISION": 32, "time": 11.0606464}, {"MWG": 64, "NWG": 32, "KWG": 32, "MDIMC": 32, "NDIMC": 8, "MDIMA": 16, "NDIMB": 32, "KWI": 2, "VWM": 2, "VWN": 1, "STRM": 0, "STRN": 0, "SA": 0, "SB": 1, "PRECISION": 32, "time": 8.957657600000001}, {"MWG": 64, "NWG": 64, "KWG": 32, "MDIMC": 16, "NDIMC": 16, "MDIMA": 16, "NDIMB": 8, "KWI": 2, "VWM": 1, "VWN": 4, "STRM": 0, "STRN": 0, "SA": 1, "SB": 0, "PRECISION": 32, "time": 7.5469632}, {"MWG": 32, "NWG": 64, "KWG": 32, "MDIMC": 8, "NDIMC": 8, "MDIMA": 8, "NDIMB": 8, "KWI": 2, "VWM": 2, "VWN": 4, "STRM": 0, "STRN": 0, "SA": 0, "SB": 1, "PRECISION": 32, "time": 4.3986176}, {"MWG": 32, "NWG": 32, "KWG": 32, "MDIMC": 16, "NDIMC": 8, "MDIMA": 16, "NDIMB": 16, "KWI": 2, "VWM": 2, "VWN": 2, "STRM": 0, "STRN": 0, "SA": 0, "SB": 0, "PRECISION": 32, "time": 15.455737599999997}, {"MWG": 64, "NWG": 64, "KWG": 32, "MDIMC": 32, "NDIMC": 16, "MDIMA": 16, "NDIMB": 16, "KWI": 2, "VWM": 2, "VWN": 2, "STRM": 0, "STRN": 0, "SA": 0, "SB": 1, "PRECISION": 32, "time": 6.609625599999999}, {"MWG": 32, "NWG": 64, "KWG": 32, "MDIMC": 8, "NDIMC": 32, "MDIMA": 8, "NDIMB": 16, "KWI": 2, "VWM": 2, "VWN": 2, "STRM": 0, "STRN": 0, "SA": 1, "SB": 1, "PRECISION": 32, "time": 7.826207999999999}, {"MWG": 64, "NWG": 64, "KWG": 32, "MDIMC": 8, "NDIMC": 16, "MDIMA": 8, "NDIMB": 16, "KWI": 2, "VWM": 2, "VWN": 2, "STRM": 0, "STRN": 0, "SA": 0, "SB": 1, "PRECISION": 32, "time": 7.313343999999999}, {"MWG": 64, "NWG": 16, "KWG": 32, "MDIMC": 32, "NDIMC": 8, "MDIMA": 32, "NDIMB": 16, "KWI": 2, "VWM": 1, "VWN": 1, "STRM": 0, "STRN": 0, "SA": 0, "SB": 1, "PRECISION": 32, "time": 11.9686016}, {"MWG": 32, "NWG": 32, "KWG": 32, "MDIMC": 8, "NDIMC": 16, "MDIMA": 16, "NDIMB": 8, "KWI": 2, "VWM": 1, "VWN": 2, "STRM": 0, "STRN": 0, "SA": 0, "SB": 1, "PRECISION": 32, "time": 21.7330112}, {"MWG": 32, "NWG": 64, "KWG": 32, "MDIMC": 8, "NDIMC": 32, "MDIMA": 8, "NDIMB": 16, "KWI": 2, "VWM": 2, "VWN": 2, "STRM": 0, "STRN": 0, "SA": 0, "SB": 0, "PRECISION": 32, "time": 15.470463999999998}, {"MWG": 32, "NWG": 32, "KWG": 32, "MDIMC": 16, "NDIMC": 16, "MDIMA": 16, "NDIMB": 16, "KWI": 2, "VWM": 2, "VWN": 2, "STRM": 0, "STRN": 0, "SA": 1, "SB": 1, "PRECISION": 32, "time": 9.0108544}, {"MWG": 64, "NWG": 32, "KWG": 32, "MDIMC": 8, "NDIMC": 16, "MDIMA": 32, "NDIMB": 32, "KWI": 2, "VWM": 2, "VWN": 1, "STRM": 0, "STRN": 0, "SA": 1, "SB": 1, "PRECISION": 32, "time": 11.708108799999998}, {"MWG": 32, "NWG": 64, "KWG": 32, "MDIMC": 16, "NDIMC": 8, "MDIMA": 16, "NDIMB": 16, "KWI": 2, "VWM": 2, "VWN": 2, "STRM": 0, "STRN": 0, "SA": 0, "SB": 1, "PRECISION": 32, "time": 4.8403328}, {"MWG": 32, "NWG": 32, "KWG": 32, "MDIMC": 16, "NDIMC": 8, "MDIMA": 16, "NDIMB": 32, "KWI": 2, "VWM": 2, "VWN": 1, "STRM": 0, "STRN": 0, "SA": 1, "SB": 1, "PRECISION": 32, "time": 6.252326399999999}, {"MWG": 64, "NWG": 64, "KWG": 32, "MDIMC": 16, "NDIMC": 8, "MDIMA": 16, "NDIMB": 8, "KWI": 2, "VWM": 2, "VWN": 2, "STRM": 0, "STRN": 0, "SA": 1, "SB": 1, "PRECISION": 32, "time": 4.9159808}, {"MWG": 32, "NWG": 64, "KWG": 32, "MDIMC": 8, "NDIMC": 16, "MDIMA": 16, "NDIMB": 16, "KWI": 2, "VWM": 1, "VWN": 2, "STRM": 0, "STRN": 0, "SA": 1, "SB": 1, "PRECISION": 32, "time": 5.531635199999999}, {"MWG": 64, "NWG": 64, "KWG": 32, "MDIMC": 8, "NDIMC": 8, "MDIMA": 8, "NDIMB": 16, "KWI": 2, "VWM": 1, "VWN": 2, "STRM": 0, "STRN": 0, "SA": 0, "SB": 0, "PRECISION": 32, "time": 6.1929536}, {"MWG": 32, "NWG": 64, "KWG": 32, "MDIMC": 8, "NDIMC": 32, "MDIMA": 16, "NDIMB": 8, "KWI": 2, "VWM": 2, "VWN": 2, "STRM": 0, "STRN": 0, "SA": 0, "SB": 1, "PRECISION": 32, "time": 11.6365568}, {"MWG": 32, "NWG": 64, "KWG": 32, "MDIMC": 8, "NDIMC": 16, "MDIMA": 16, "NDIMB": 32, "KWI": 2, "VWM": 1, "VWN": 2, "STRM": 0, "STRN": 0, "SA": 0, "SB": 0, "PRECISION": 32, "time": 15.439961599999998}, {"MWG": 32, "NWG": 32, "KWG": 32, "MDIMC": 16, "NDIMC": 8, "MDIMA": 32, "NDIMB": 8, "KWI": 2, "VWM": 1, "VWN": 4, "STRM": 0, "STRN": 0, "SA": 0, "SB": 0, "PRECISION": 32, "time": 15.4802368}, {"MWG": 64, "NWG": 64, "KWG": 32, "MDIMC": 32, "NDIMC": 16, "MDIMA": 32, "NDIMB": 16, "KWI": 2, "VWM": 2, "VWN": 4, "STRM": 0, "STRN": 0, "SA": 0, "SB": 0, "PRECISION": 32, "time": 15.652275199999997}, {"MWG": 64, "NWG": 64, "KWG": 32, "MDIMC": 8, "NDIMC": 16, "MDIMA": 8, "NDIMB": 8, "KWI": 2, "VWM": 2, "VWN": 4, "STRM": 0, "STRN": 0, "SA": 0, "SB": 0, "PRECISION": 32, "time": 8.544352}, {"MWG": 64, "NWG": 64, "KWG": 32, "MDIMC": 32, "NDIMC": 16, "MDIMA": 32, "NDIMB": 32, "KWI": 2, "VWM": 1, "VWN": 2, "STRM": 0, "STRN": 0, "SA": 0, "SB": 1, "PRECISION": 32, "time": 7.069145600000001}, {"MWG": 64, "NWG": 64, "KWG": 32, "MDIMC": 8, "NDIMC": 16, "MDIMA": 8, "NDIMB": 8, "KWI": 2, "VWM": 4, "VWN": 4, "STRM": 0, "STRN": 0, "SA": 1, "SB": 1, "PRECISION": 32, "time": 6.629932799999999}, {"MWG": 32, "NWG": 32, "KWG": 32, "MDIMC": 16, "NDIMC": 16, "MDIMA": 16, "NDIMB": 16, "KWI": 2, "VWM": 2, "VWN": 2, "STRM": 0, "STRN": 0, "SA": 0, "SB": 1, "PRECISION": 32, "time": 11.0309056}, {"MWG": 32, "NWG": 32, "KWG": 32, "MDIMC": 16, "NDIMC": 16, "MDIMA": 16, "NDIMB": 8, "KWI": 2, "VWM": 2, "VWN": 1, "STRM": 0, "STRN": 0, "SA": 0, "SB": 1, "PRECISION": 32, "time": 12.928665599999999}, {"MWG": 64, "NWG": 64, "KWG": 32, "MDIMC": 32, "NDIMC": 8, "MDIMA": 32, "NDIMB": 16, "KWI": 2, "VWM": 2, "VWN": 1, "STRM": 0, "STRN": 0, "SA": 1, "SB": 0, "PRECISION": 32, "time": 11.437798399999998}, {"MWG": 64, "NWG": 32, "KWG": 32, "MDIMC": 8, "NDIMC": 16, "MDIMA": 16, "NDIMB": 8, "KWI": 2, "VWM": 4, "VWN": 1, "STRM": 0, "STRN": 0, "SA": 0, "SB": 0, "PRECISION": 32, "time": 13.1374272}, {"MWG": 64, "NWG": 32, "KWG": 32, "MDIMC": 16, "NDIMC": 16, "MDIMA": 16, "NDIMB": 32, "KWI": 2, "VWM": 2, "VWN": 1, "STRM": 0, "STRN": 0, "SA": 0, "SB": 1, "PRECISION": 32, "time": 21.094047999999997}, {"MWG": 64, "NWG": 64, "KWG": 32, "MDIMC": 8, "NDIMC": 8, "MDIMA": 32, "NDIMB": 16, "KWI": 2, "VWM": 2, "VWN": 1, "STRM": 0, "STRN": 0, "SA": 0, "SB": 1, "PRECISION": 32, "time": 7.222303999999999}, {"MWG": 64, "NWG": 32, "KWG": 32, "MDIMC": 16, "NDIMC": 16, "MDIMA": 16, "NDIMB": 8, "KWI": 2, "VWM": 1, "VWN": 2, "STRM": 0, "STRN": 0, "SA": 0, "SB": 0, "PRECISION": 32, "time": 43.7061376}, {"MWG": 32, "NWG": 64, "KWG": 32, "MDIMC": 16, "NDIMC": 8, "MDIMA": 16, "NDIMB": 8, "KWI": 2, "VWM": 2, "VWN": 4, "STRM": 0, "STRN": 0, "SA": 0, "SB": 0, "PRECISION": 32, "time": 13.0564032}, {"MWG": 64, "NWG": 32, "KWG": 32, "MDIMC": 32, "NDIMC": 8, "MDIMA": 16, "NDIMB": 16, "KWI": 2, "VWM": 1, "VWN": 2, "STRM": 0, "STRN": 0, "SA": 1, "SB": 1, "PRECISION": 32, "time": 9.2284544}, {"MWG": 32, "NWG": 32, "KWG": 32, "MDIMC": 16, "NDIMC": 16, "MDIMA": 16, "NDIMB": 16, "KWI": 2, "VWM": 2, "VWN": 2, "STRM": 0, "STRN": 0, "SA": 1, "SB": 0, "PRECISION": 32, "time": 11.0464128}, {"MWG": 32, "NWG": 32, "KWG": 32, "MDIMC": 16, "NDIMC": 16, "MDIMA": 32, "NDIMB": 8, "KWI": 2, "VWM": 1, "VWN": 2, "STRM": 0, "STRN": 0, "SA": 0, "SB": 0, "PRECISION": 32, "time": 20.484915199999996}, {"MWG": 32, "NWG": 32, "KWG": 32, "MDIMC": 8, "NDIMC": 16, "MDIMA": 32, "NDIMB": 8, "KWI": 2, "VWM": 1, "VWN": 2, "STRM": 0, "STRN": 0, "SA": 1, "SB": 0, "PRECISION": 32, "time": 9.0341056}, {"MWG": 64, "NWG": 64, "KWG": 32, "MDIMC": 16, "NDIMC": 16, "MDIMA": 32, "NDIMB": 16, "KWI": 2, "VWM": 2, "VWN": 2, "STRM": 0, "STRN": 0, "SA": 0, "SB": 1, "PRECISION": 32, "time": 11.1822656}, {"MWG": 64, "NWG": 32, "KWG": 32, "MDIMC": 8, "NDIMC": 8, "MDIMA": 8, "NDIMB": 16, "KWI": 2, "VWM": 2, "VWN": 1, "STRM": 0, "STRN": 0, "SA": 1, "SB": 1, "PRECISION": 32, "time": 8.047980800000001}, {"MWG": 32, "NWG": 64, "KWG": 32, "MDIMC": 16, "NDIMC": 32, "MDIMA": 16, "NDIMB": 16, "KWI": 2, "VWM": 2, "VWN": 2, "STRM": 0, "STRN": 0, "SA": 1, "SB": 0, "PRECISION": 32, "time": 10.786374400000001}, {"MWG": 64, "NWG": 64, "KWG": 32, "MDIMC": 16, "NDIMC": 16, "MDIMA": 16, "NDIMB": 32, "KWI": 2, "VWM": 2, "VWN": 1, "STRM": 0, "STRN": 0, "SA": 1, "SB": 0, "PRECISION": 32, "time": 6.395878399999999}, {"MWG": 32, "NWG": 64, "KWG": 32, "MDIMC": 16, "NDIMC": 16, "MDIMA": 16, "NDIMB": 8, "KWI": 2, "VWM": 2, "VWN": 2, "STRM": 0, "STRN": 0, "SA": 0, "SB": 1, "PRECISION": 32, "time": 6.994790399999999}, {"MWG": 64, "NWG": 32, "KWG": 32, "MDIMC": 8, "NDIMC": 16, "MDIMA": 8, "NDIMB": 8, "KWI": 2, "VWM": 4, "VWN": 2, "STRM": 0, "STRN": 0, "SA": 0, "SB": 1, "PRECISION": 32, "time": 10.932755199999999}, {"MWG": 32, "NWG": 32, "KWG": 32, "MDIMC": 16, "NDIMC": 8, "MDIMA": 8, "NDIMB": 16, "KWI": 2, "VWM": 2, "VWN": 1, "STRM": 0, "STRN": 0, "SA": 0, "SB": 1, "PRECISION": 32, "time": 9.015155199999999}, {"MWG": 32, "NWG": 32, "KWG": 32, "MDIMC": 16, "NDIMC": 16, "MDIMA": 8, "NDIMB": 16, "KWI": 2, "VWM": 2, "VWN": 2, "STRM": 0, "STRN": 0, "SA": 1, "SB": 1, "PRECISION": 32, "time": 9.093888000000002}, {"MWG": 32, "NWG": 64, "KWG": 32, "MDIMC": 16, "NDIMC": 8, "MDIMA": 16, "NDIMB": 16, "KWI": 2, "VWM": 2, "VWN": 2, "STRM": 0, "STRN": 0, "SA": 0, "SB": 1, "PRECISION": 32, "time": 4.8357567999999995}, {"MWG": 64, "NWG": 32, "KWG": 32, "MDIMC": 16, "NDIMC": 16, "MDIMA": 16, "NDIMB": 8, "KWI": 2, "VWM": 1, "VWN": 2, "STRM": 0, "STRN": 0, "SA": 0, "SB": 1, "PRECISION": 32, "time": 41.1238272}, {"MWG": 64, "NWG": 64, "KWG": 32, "MDIMC": 32, "NDIMC": 16, "MDIMA": 32, "NDIMB": 16, "KWI": 2, "VWM": 2, "VWN": 4, "STRM": 0, "STRN": 0, "SA": 0, "SB": 1, "PRECISION": 32, "time": 5.7896768}, {"MWG": 64, "NWG": 64, "KWG": 32, "MDIMC": 32, "NDIMC": 8, "MDIMA": 16, "NDIMB": 16, "KWI": 2, "VWM": 2, "VWN": 4, "STRM": 0, "STRN": 0, "SA": 0, "SB": 1, "PRECISION": 32, "time": 4.3258431999999996}, {"MWG": 64, "NWG": 64, "KWG": 32, "MDIMC": 16, "NDIMC": 16, "MDIMA": 8, "NDIMB": 16, "KWI": 2, "VWM": 2, "VWN": 4, "STRM": 0, "STRN": 0, "SA": 0, "SB": 1, "PRECISION": 32, "time": 10.846739199999998}, {"MWG": 64, "NWG": 64, "KWG": 32, "MDIMC": 16, "NDIMC": 32, "MDIMA": 32, "NDIMB": 16, "KWI": 2, "VWM": 1, "VWN": 2, "STRM": 0, "STRN": 0, "SA": 1, "SB": 1, "PRECISION": 32, "time": 12.2170176}, {"MWG": 64, "NWG": 32, "KWG": 32, "MDIMC": 16, "NDIMC": 16, "MDIMA": 16, "NDIMB": 8, "KWI": 2, "VWM": 4, "VWN": 1, "STRM": 0, "STRN": 0, "SA": 0, "SB": 1, "PRECISION": 32, "time": 11.630911999999999}, {"MWG": 32, "NWG": 32, "KWG": 32, "MDIMC": 8, "NDIMC": 8, "MDIMA": 16, "NDIMB": 8, "KWI": 2, "VWM": 2, "VWN": 4, "STRM": 0, "STRN": 0, "SA": 1, "SB": 1, "PRECISION": 32, "time": 4.9334656}, {"MWG": 64, "NWG": 64, "KWG": 32, "MDIMC": 16, "NDIMC": 16, "MDIMA": 32, "NDIMB": 32, "KWI": 2, "VWM": 2, "VWN": 2, "STRM": 0, "STRN": 0, "SA": 1, "SB": 0, "PRECISION": 32, "time": 6.6132672}, {"MWG": 64, "NWG": 64, "KWG": 32, "MDIMC": 16, "NDIMC": 32, "MDIMA": 16, "NDIMB": 32, "KWI": 2, "VWM": 4, "VWN": 2, "STRM": 0, "STRN": 0, "SA": 0, "SB": 0, "PRECISION": 32, "time": 15.642406399999999}, {"MWG": 32, "NWG": 32, "KWG": 32, "MDIMC": 16, "NDIMC": 16, "MDIMA": 16, "NDIMB": 16, "KWI": 2, "VWM": 2, "VWN": 2, "STRM": 0, "STRN": 0, "SA": 0, "SB": 1, "PRECISION": 32, "time": 11.036582399999999}, {"MWG": 64, "NWG": 64, "KWG": 32, "MDIMC": 32, "NDIMC": 16, "MDIMA": 16, "NDIMB": 16, "KWI": 2, "VWM": 2, "VWN": 2, "STRM": 0, "STRN": 0, "SA": 1, "SB": 0, "PRECISION": 32, "time": 10.94688}, {"MWG": 32, "NWG": 32, "KWG": 32, "MDIMC": 16, "NDIMC": 16, "MDIMA": 8, "NDIMB": 16, "KWI": 2, "VWM": 1, "VWN": 1, "STRM": 0, "STRN": 0, "SA": 0, "SB": 0, "PRECISION": 32, "time": 21.476723200000002}, {"MWG": 32, "NWG": 32, "KWG": 32, "MDIMC": 16, "NDIMC": 16, "MDIMA": 16, "NDIMB": 16, "KWI": 2, "VWM": 2, "VWN": 2, "STRM": 0, "STRN": 0, "SA": 0, "SB": 0, "PRECISION": 32, "time": 20.7505344}, {"MWG": 64, "NWG": 64, "KWG": 32, "MDIMC": 16, "NDIMC": 16, "MDIMA": 8, "NDIMB": 8, "KWI": 2, "VWM": 2, "VWN": 4, "STRM": 0, "STRN": 0, "SA": 0, "SB": 1, "PRECISION": 32, "time": 10.950169599999999}, {"MWG": 32, "NWG": 64, "KWG": 32, "MDIMC": 16, "NDIMC": 16, "MDIMA": 16, "NDIMB": 16, "KWI": 2, "VWM": 1, "VWN": 4, "STRM": 0, "STRN": 0, "SA": 0, "SB": 0, "PRECISION": 32, "time": 15.658784}, {"MWG": 32, "NWG": 64, "KWG": 32, "MDIMC": 16, "NDIMC": 16, "MDIMA": 16, "NDIMB": 16, "KWI": 2, "VWM": 2, "VWN": 4, "STRM": 0, "STRN": 0, "SA": 0, "SB": 1, "PRECISION": 32, "time": 6.0774592}, {"MWG": 32, "NWG": 64, "KWG": 32, "MDIMC": 16, "NDIMC": 8, "MDIMA": 16, "NDIMB": 32, "KWI": 2, "VWM": 2, "VWN": 2, "STRM": 0, "STRN": 0, "SA": 1, "SB": 1, "PRECISION": 32, "time": 5.2693888}, {"MWG": 32, "NWG": 64, "KWG": 32, "MDIMC": 16, "NDIMC": 16, "MDIMA": 16, "NDIMB": 16, "KWI": 2, "VWM": 2, "VWN": 2, "STRM": 0, "STRN": 0, "SA": 1, "SB": 0, "PRECISION": 32, "time": 10.839936}, {"MWG": 64, "NWG": 64, "KWG": 32, "MDIMC": 16, "NDIMC": 16, "MDIMA": 16, "NDIMB": 16, "KWI": 2, "VWM": 2, "VWN": 4, "STRM": 0, "STRN": 0, "SA": 0, "SB": 0, "PRECISION": 32, "time": 14.0927808}, {"MWG": 64, "NWG": 64, "KWG": 32, "MDIMC": 16, "NDIMC": 8, "MDIMA": 16, "NDIMB": 16, "KWI": 2, "VWM": 2, "VWN": 2, "STRM": 0, "STRN": 0, "SA": 0, "SB": 1, "PRECISION": 32, "time": 6.257945600000001}, {"MWG": 32, "NWG": 64, "KWG": 32, "MDIMC": 8, "NDIMC": 16, "MDIMA": 16, "NDIMB": 16, "KWI": 2, "VWM": 2, "VWN": 2, "STRM": 0, "STRN": 0, "SA": 1, "SB": 0, "PRECISION": 32, "time": 6.5827136}, {"MWG": 32, "NWG": 32, "KWG": 32, "MDIMC": 16, "NDIMC": 16, "MDIMA": 16, "NDIMB": 16, "KWI": 2, "VWM": 2, "VWN": 1, "STRM": 0, "STRN": 0, "SA": 1, "SB": 0, "PRECISION": 32, "time": 11.7946496}, {"MWG": 32, "NWG": 64, "KWG": 32, "MDIMC": 8, "NDIMC": 8, "MDIMA": 8, "NDIMB": 16, "KWI": 2, "VWM": 1, "VWN": 2, "STRM": 0, "STRN": 0, "SA": 0, "SB": 1, "PRECISION": 32, "time": 6.6325632}, {"MWG": 32, "NWG": 64, "KWG": 32, "MDIMC": 16, "NDIMC": 16, "MDIMA": 16, "NDIMB": 8, "KWI": 2, "VWM": 2, "VWN": 2, "STRM": 0, "STRN": 0, "SA": 1, "SB": 0, "PRECISION": 32, "time": 10.838579200000002}, {"MWG": 64, "NWG": 32, "KWG": 32, "MDIMC": 8, "NDIMC": 16, "MDIMA": 16, "NDIMB": 16, "KWI": 2, "VWM": 4, "VWN": 2, "STRM": 0, "STRN": 0, "SA": 1, "SB": 0, "PRECISION": 32, "time": 11.002348799999998}, {"MWG": 64, "NWG": 32, "KWG": 32, "MDIMC": 8, "NDIMC": 32, "MDIMA": 16, "NDIMB": 16, "KWI": 2, "VWM": 4, "VWN": 1, "STRM": 0, "STRN": 0, "SA": 1, "SB": 1, "PRECISION": 32, "time": 22.7710336}]